scan_service/main.py
scan_service/lib/__init__.py
scan_service/lib/common/__init__.py
scan_service/lib/common/base/__init__.py
scan_service/lib/common/base/base_parse.py
scan_service/lib/common/base/base_scan.py
scan_service/lib/common/java/__init__.py
scan_service/lib/common/java/java_scan.py
scan_service/lib/database/__init__.py
scan_service/lib/database/table.py
scan_service/lib/framework/__init__.py
scan_service/lib/framework/concurrent_utility.py
scan_service/lib/framework/exception.py
scan_service/lib/framework/log_utility.py
scan_service/lib/framework/progress.py
scan_service/lib/framework/result.py
scan_service/lib/modules/__init__.py
scan_service/lib/modules/AIX/__init__.py
scan_service/lib/modules/AIX/scan_aix.py
scan_service/lib/modules/apache/__init__.py
scan_service/lib/modules/apache/parse_apache.py
scan_service/lib/modules/apache/scan_apache.py
scan_service/lib/modules/esxi/__init__.py
scan_service/lib/modules/esxi/scan_esxi.py
scan_service/lib/modules/keepalived/__init__.py
scan_service/lib/modules/keepalived/parse_keepalived.py
scan_service/lib/modules/keepalived/scan_keepalived.py
scan_service/lib/modules/linux/__init__.py
scan_service/lib/modules/linux/scan_linux.py
scan_service/lib/modules/load_balance/__init__.py
scan_service/lib/modules/load_balance/scan_f5.py
scan_service/lib/modules/load_balance/scan_sangfor.py
scan_service/lib/modules/mysql/__init__.py
scan_service/lib/modules/mysql/parse_mysql.py
scan_service/lib/modules/mysql/scan_mysql.py
scan_service/lib/modules/network_device/__init__.py
scan_service/lib/modules/network_device/scan_switch.py
scan_service/lib/modules/network_device/Cisco/__init__.py
scan_service/lib/modules/network_device/Cisco/scan_cisco_router.py
scan_service/lib/modules/network_device/Cisco/scan_cisco_switch.py
scan_service/lib/modules/network_device/DPtech/__init__.py
scan_service/lib/modules/network_device/DPtech/scan_dptech_router.py
scan_service/lib/modules/network_device/DPtech/scan_dptech_switch.py
scan_service-0.0.10.dist-info/LICENSE
scan_service-0.0.10.dist-info/METADATA
scan_service-0.0.10.dist-info/WHEEL
scan_service-0.0.10.dist-info/top_level.txt
scan_service-0.0.10.dist-info/RECORD
