Metadata-Version: 2.1
Name: scan-service
Version: 0.0.10
Summary: scan IT resources using ssh, snmp, wmi
Author-email: LiamLea <liweixiliang@gmail.com>
Classifier: Programming Language :: Python :: 3
Classifier: License :: OSI Approved :: MIT License
Classifier: Operating System :: OS Independent
Requires-Python: >=3.6
License-File: LICENSE
